{
    "objectives_title": "Mục Tiêu",
    "objectives_modal_side_nav_aria_label_lol_tab": "Chọn Liên Minh Huyền Thoại",
    "objectives_modal_side_nav_aria_label_tft_tab": "Chọn Đấu Trường Chân Lý",
    "objectives_modal_main_refresh_subtext_weekly": "Nhiệm Vụ Mới: {{remainingTime}}",
    "objectives_modal_main_refresh_subtext_daily": "Làm Mới {{remainingTime}}",
    "objectives_modal_acc_completed": "Đã Hoàn Thành",
    "objectives_modal_acc_expiring": "Sắp Hết Hạn",
    "objectives_divider_text_or": "HOẶC",
    "objectives_divider_text_and": "VÀ",
    "objectives_title_recurring": "(Lặp Lại)",
    "season_pass_free_reward": "Phần Thưởng Miễn Phí",
    "season_pass_premium_reward": "Phần Thưởng Tiếp Theo",
    "season_pass_view_reward": "Xem Pass",
    "season_pass_level": "Cấp {{level}}",
    "season_pass_XP": "BXP",
    "objectives_tft_header": "Mục Tiêu ĐTCL",
    "season_pass_tooltip_text": "Phần Thưởng kế tiếp yêu cầu nâng cấp Vé Sự Kiện.",
    "objectives_error_state_text": "Đã xảy ra trục trặc, nhưng những mục tiêu đã hoàn thành trong thời gian này sẽ được trao thưởng khi lỗi được khắc phục. Vui lòng quay lại sau.",
    "season_pass_error_state_text": "Đã xảy ra trục trặc ở đây, nhưng bạn sẽ không bị mất tiến trình của mình. Vui lòng quay lại sau.",
    "season_pass_error_state_title": "Vé Sự Kiện",
    "objectives_full_error_state": "Đã có lỗi xảy ra. Vui lòng quay lại sau.",
    "objectives_freeze_state_text": "Mục Tiêu & Vé Sắp Ra Mắt",
    "objectives_extra_description": "Các trận Xếp Hạng Mùa Giải được theo dõi liên tục xuyên suốt mùa giải",
    "objectives_grace_period_text": "Mục Tiêu Mới Sắp Ra Mắt",
    "objectives_reward_tooltip_end_timer_text": "{{remainingTime}}",
    "objectives_reward_tooltip_completed_time_text": "Đã hoàn thành vào {{completedDate}}",
    "objectives_sub_nav_expiring_text": "{{remainingTime}}",
    "objectives_battlepass_xp": "BXP",
    "objectives_hol_xp": "Cấp",
    "objectives_hol_xp_level": "Cấp",
    "level_out_of_total": "Cấp {{level}} / {{total}}",
    "pass_header_pass_start": "Bắt Đầu",
    "show_completed_checkbox": "Hiển Thị Đã Hoàn Thành",
    "objectives_pass_completed": "Battle Pass Đã Hoàn Tất!",
    "generic_xp": "XP"
}