{
    "Characters/TFT15_XinZhao/Skins/Root": {
        "skinAudioProperties": {
            "tagEventList": [
                "TFT15_XinZhao"
            ],
            "__type": "SkinAudioProperties"
        },
        "skinAnimationProperties": {
            "animationGraphData": "{bfeb16e2}",
            "__type": "SkinAnimationProperties"
        },
        "skinMeshProperties": {
            "skinScale": 0.949999988079071,
            "__type": "SkinMeshDataProperties"
        },
        "healthBarData": {
            "hpPerTick": 300.0,
            "unitHealthBarStyle": 15,
            "showWhileUntargetable": true,
            "AlphaOutWhileUntargetable": false,
            "__type": "CharacterHealthBarDataRecord"
        },
        "__type": "TftSkinCharacterDataProperties"
    },
    "__linked": [
        "Characters/TFT15_XinZhao",
        "DATA/Characters/TFT15_XinZhao/Animations/Skin0.bin"
    ]
}