{
    "Characters/Sru_Duck/Skins/Skin0": {
        "championSkinName": "SruDuck",
        "skinAnimationProperties": {
            "animationGraphData": "Characters/Sru_Duck/Animations/Skin0",
            "__type": "SkinAnimationProperties"
        },
        "skinMeshProperties": {
            "skeleton": "ASSETS/Characters/Sru_Duck/Skins/Base/Sru_Duck.skl",
            "simpleSkin": "ASSETS/Characters/Sru_Duck/Skins/Base/Sru_Duck.skn",
            "texture": "ASSETS/Characters/Sru_Duck/Skins/Base/Sru_Duck_TX_CM.tex",
            "skinScale": 0.699999988079071,
            "selfIllumination": 0.699999988079071,
            "reflectionFresnelColor": [
                0,
                0,
                0,
                255
            ],
            "__type": "SkinMeshDataProperties"
        },
        "armorMaterial": "Flesh",
        "__type": "SkinCharacterDataProperties"
    },
    "__linked": [
        "DATA/Characters/Sru_Duck/Sru_Duck.bin",
        "DATA/Characters/Sru_Duck/Animations/Skin0.bin"
    ]
}